hhcli/__init__.py
hhcli/client.py
hhcli/constants.py
hhcli/database.py
hhcli/main.py
hhcli/mimicry.py
hhcli/reference_data.py
hhcli/ui/__init__.py
hhcli/ui/app.py
hhcli/ui/css_manager.py
hhcli/ui/dialogs/__init__.py
hhcli/ui/dialogs/apply_confirmation.py
hhcli/ui/dialogs/confirm_code.py
hhcli/ui/dialogs/profile_create.py
hhcli/ui/dialogs/resume_select.py
hhcli/ui/modules/__init__.py
hhcli/ui/modules/apply_service.py
hhcli/ui/modules/dictionaries.py
hhcli/ui/modules/history_service.py
hhcli/ui/modules/vacancy_service.py
hhcli/ui/screens/__init__.py
hhcli/ui/screens/config.py
hhcli/ui/screens/history.py
hhcli/ui/screens/profile_select.py
hhcli/ui/screens/search_mode.py
hhcli/ui/screens/vacancy_list.py
hhcli/ui/scrollbars.py
hhcli/ui/theme.py
hhcli/ui/themes/__init__.py
hhcli/ui/themes/base.tcss
hhcli/ui/themes/design_system.tcss
hhcli/ui/themes/dracula.tcss
hhcli/ui/themes/github_light.tcss
hhcli/ui/themes/gruvbox_dark.tcss
hhcli/ui/themes/monokai.tcss
hhcli/ui/themes/nord.tcss
hhcli/ui/themes/one_dark.tcss
hhcli/ui/themes/solarized_dark.tcss
hhcli/ui/themes/tokyo_night.tcss
hhcli/ui/tui.py
hhcli/ui/utils/__init__.py
hhcli/ui/utils/constants.py
hhcli/ui/utils/formatting.py
hhcli/ui/utils/statuses.py
hhcli/ui/widgets/__init__.py
hhcli/ui/widgets/history_panel.py
hhcli/ui/widgets/pagination.py
hhcli/ui/widgets/selection_lists.py
hhcli/version.py
hhcli-0.6.2.dist-info/METADATA
hhcli-0.6.2.dist-info/WHEEL
hhcli-0.6.2.dist-info/entry_points.txt
hhcli-0.6.2.dist-info/licenses/LICENSE
hhcli-0.6.2.dist-info/RECORD
