Metadata-Version: 2.4
Name: hhcli
Version: 0.6.2
Summary: Неофициальный CLI-клиент для поиска работы и откликов на hh.ru.
License: MIT
License-File: LICENSE
Author: fovendor
Author-email: fovendor@gmail.com
Requires-Python: >=3.9,<4.0
Classifier: License :: OSI Approved :: MIT License
Classifier: Programming Language :: Python :: 3
Classifier: Programming Language :: Python :: 3.9
Classifier: Programming Language :: Python :: 3.10
Classifier: Programming Language :: Python :: 3.11
Classifier: Programming Language :: Python :: 3.12
Classifier: Programming Language :: Python :: 3.13
Classifier: Programming Language :: Python :: 3.14
Requires-Dist: flask (>=3.0.0,<4.0.0)
Requires-Dist: html2text (>=2025.4.15,<2026.0.0)
Requires-Dist: platformdirs (>=4.0.0,<5.0.0)
Requires-Dist: pywebview (>=5,<6)
Requires-Dist: requests (>=2.31.0,<3.0.0)
Requires-Dist: sqlalchemy (>=2.0.23,<3.0.0)
Requires-Dist: textual
